django_activitypub
