Metadata-Version: 2.1
Name: django-activitypub
Version: 0.0.2
Summary: A Django app implementing the ActivityPub protocol
Home-page: https://sam.sutch.net/projects/django-activitypub
Author: Samuel Sutch
Author-email: sam@sutch.net
License: BSD-3-Clause
Classifier: Environment :: Web Environment
Classifier: Framework :: Django
Classifier: Framework :: Django :: 4.2
Classifier: Intended Audience :: Developers
Classifier: License :: OSI Approved :: BSD License
Classifier: Operating System :: OS Independent
Classifier: Programming Language :: Python
Classifier: Programming Language :: Python :: 3
Classifier: Programming Language :: Python :: 3 :: Only
Classifier: Programming Language :: Python :: 3.11
Classifier: Programming Language :: Python :: 3.12
Classifier: Topic :: Internet :: WWW/HTTP
Classifier: Topic :: Internet :: WWW/HTTP :: Dynamic Content
Requires-Python: >=3.11
License-File: LICENSE
Requires-Dist: django>=4.2
Requires-Dist: Pillow>=10.1.0
Requires-Dist: cryptography>=41.0.0
Requires-Dist: requests>=2.31.0
Requires-Dist: Markdown>=3.5.0
Requires-Dist: django-tree-queries>=0.16.1
Requires-Dist: html-sanitizer>=2.2.0
